[{"adId":14,"campaignId":8091,"keyWords":["xbox+360+video+games+"],"relevanceScore":0.0,"pClick":0.0,"bidPrice":4.5,"rankScore":0.0,"qualityScore":0.0,"costPerClick":0.0,"position":0,"title":"Mx Vs ATV Untamed - Xbox 360","price":17.88,"thumbnail":"https://images-na.ssl-images-amazon.com/images/I/61GwfFvA8qL._AC_US218_.jpg","description":null,"brand":"","detail_url":"https://www.amazon.com/dp/B000TP2V3A","query":"xbox 360 video games ","query_group_id":0,"category":"Video Games"},{"adId":14,"campaignId":8091,"keyWords":["xbox+360+video+games+"],"relevanceScore":0.0,"pClick":0.0,"bidPrice":4.5,"rankScore":0.0,"qualityScore":0.0,"costPerClick":0.0,"position":0,"title":"Minecraft","price":14.39,"thumbnail":"https://images-na.ssl-images-amazon.com/images/I/51EYPFcLK9L._AC_US218_.jpg","description":"... interface in Minecraft for Xbox 360 delivers a completely new way ...","brand":"","detail_url":"https://www.amazon.com/dp/B00BU3ZLJQ","query":"xbox 360 video games ","query_group_id":0,"category":"Video Games"},{"adId":14,"campaignId":8091,"keyWords":["xbox+360+video+games+"],"relevanceScore":0.0,"pClick":0.0,"bidPrice":4.5,"rankScore":0.0,"qualityScore":0.0,"costPerClick":0.0,"position":0,"title":"Mortal Kombat: Komplete Edition - Xbox 360","price":19.99,"thumbnail":"https://images-na.ssl-images-amazon.com/images/I/510ILE3WVcL._AC_US218_.jpg","description":"Platform: Xbox 360","brand":"","detail_url":"https://www.amazon.com/dp/B006ZTHGCK","query":"xbox 360 video games ","query_group_id":0,"category":"Video Games"},{"adId":14,"campaignId":8091,"keyWords":["xbox+360+video+games+"],"relevanceScore":0.0,"pClick":0.0,"bidPrice":4.5,"rankScore":0.0,"qualityScore":0.0,"costPerClick":0.0,"position":0,"title":"Lego: Marvel Super Heroes, XBOX 360","price":15.19,"thumbnail":"https://images-na.ssl-images-amazon.com/images/I/51rQJ6ODN8L._AC_US218_.jpg","description":null,"brand":"","detail_url":"https://www.amazon.com/dp/B00B98HF1O","query":"xbox 360 video games ","query_group_id":0,"category":"Video Games"},{"adId":14,"campaignId":8091,"keyWords":["xbox+360+video+games+"],"relevanceScore":0.0,"pClick":0.0,"bidPrice":4.5,"rankScore":0.0,"qualityScore":0.0,"costPerClick":0.0,"position":0,"title":"Cars 3: Driven to Win - Xbox 360","price":46.97,"thumbnail":"https://images-na.ssl-images-amazon.com/images/I/51jwdRp6OKL._AC_US218_.jpg","description":"... two-wheel driving, barrel rolls and more in 6 thrilling game modes. ...","brand":"","detail_url":"https://www.amazon.com/dp/B06XX58VJV","query":"xbox 360 video games ","query_group_id":0,"category":"Video Games"},{"adId":14,"campaignId":8091,"keyWords":["xbox+360+video+games+"],"relevanceScore":0.0,"pClick":0.0,"bidPrice":4.5,"rankScore":0.0,"qualityScore":0.0,"costPerClick":0.0,"position":0,"title":"Sonic & All-Stars Racing Transformed - Xbox 360","price":14.9,"thumbnail":"https://images-na.ssl-images-amazon.com/images/I/51HeSKOCQeL._AC_US218_.jpg","description":null,"brand":"","detail_url":"https://www.amazon.com/dp/B008OQTRYW","query":"xbox 360 video games ","query_group_id":0,"category":"Video Games"},{"adId":14,"campaignId":8091,"keyWords":["xbox+360+video+games+"],"relevanceScore":0.0,"pClick":0.0,"bidPrice":4.5,"rankScore":0.0,"qualityScore":0.0,"costPerClick":0.0,"position":0,"title":"Portal 2 - Xbox 360","price":36.6,"thumbnail":"https://images-na.ssl-images-amazon.com/images/I/51f-BE49+uL._AC_US218_.jpg","description":"... sequel to the title named 2007's Game of the Year by over 30 ...","brand":"","detail_url":"https://www.amazon.com/dp/B002I0J9M0","query":"xbox 360 video games ","query_group_id":0,"category":"Video Games"},{"adId":14,"campaignId":8091,"keyWords":["xbox+360+video+games+"],"relevanceScore":0.0,"pClick":0.0,"bidPrice":4.5,"rankScore":0.0,"qualityScore":0.0,"costPerClick":0.0,"position":0,"title":"Sonic Generations - Xbox 360","price":13.16,"thumbnail":"https://images-na.ssl-images-amazon.com/images/I/61JhrvcNJLL._AC_US218_.jpg","description":"... hidden treasures gradually being revealed throughout the game ...","brand":"","detail_url":"https://www.amazon.com/dp/B004X56OU8","query":"xbox 360 video games ","query_group_id":0,"category":"Video Games"},{"adId":14,"campaignId":8091,"keyWords":["xbox+360+video+games+"],"relevanceScore":0.0,"pClick":0.0,"bidPrice":4.5,"rankScore":0.0,"qualityScore":0.0,"costPerClick":0.0,"position":0,"title":"Hot Wheels World's Best Driver - Xbox 360 Standard Edition","price":12.15,"thumbnail":"https://images-na.ssl-images-amazon.com/images/I/61-EMdtjM0L._AC_US218_.jpg","description":"... Developed by Firebrand Games (NASCAR Unleashed, Cars 2, Need for Speed ...","brand":"","detail_url":"https://www.amazon.com/dp/B00EFL2R2O","query":"xbox 360 video games ","query_group_id":0,"category":"Video Games"},{"adId":14,"campaignId":8091,"keyWords":["xbox+360+video+games+"],"relevanceScore":0.0,"pClick":0.0,"bidPrice":4.5,"rankScore":0.0,"qualityScore":0.0,"costPerClick":0.0,"position":0,"title":"Call of Duty: Modern Warfare 3 - Xbox 360","price":12.49,"thumbnail":"https://images-na.ssl-images-amazon.com/images/I/51peLJez3WL._AC_US218_.jpg","description":null,"brand":"","detail_url":"https://www.amazon.com/dp/B00503E8S2","query":"xbox 360 video games ","query_group_id":0,"category":"Video Games"},{"adId":14,"campaignId":8091,"keyWords":["xbox+360+video+games+"],"relevanceScore":0.0,"pClick":0.0,"bidPrice":4.5,"rankScore":0.0,"qualityScore":0.0,"costPerClick":0.0,"position":0,"title":"LEGO Jurassic World - Xbox 360 Standard Edition","price":14.39,"thumbnail":"https://images-na.ssl-images-amazon.com/images/I/51NqU7gEX5L._AC_US218_.jpg","description":"... in LEGO form and told in TT Games' signature classic LEGO humor ...","brand":"","detail_url":"https://www.amazon.com/dp/B00SXEOOHU","query":"xbox 360 video games ","query_group_id":0,"category":"Video Games"},{"adId":14,"campaignId":8091,"keyWords":["xbox+360+video+games+"],"relevanceScore":0.0,"pClick":0.0,"bidPrice":4.5,"rankScore":0.0,"qualityScore":0.0,"costPerClick":0.0,"position":0,"title":"Assassin's Creed - Ezio Trilogy Edition xbox 360","price":18.0,"thumbnail":"https://images-na.ssl-images-amazon.com/images/I/51fL5JsQmsL._AC_US218_.jpg","description":"... numerous accolades including Game(s) of the Year, ASSASSIN'S CREED ...","brand":"","detail_url":"https://www.amazon.com/dp/B00EVWZHLK","query":"xbox 360 video games ","query_group_id":0,"category":"Video Games"},{"adId":14,"campaignId":8091,"keyWords":["xbox+360+video+games+"],"relevanceScore":0.0,"pClick":0.0,"bidPrice":4.5,"rankScore":0.0,"qualityScore":0.0,"costPerClick":0.0,"position":0,"title":"Minecraft: Story Mode- The Complete Adventure - Xbox 360","price":19.93,"thumbnail":"https://images-na.ssl-images-amazon.com/images/I/515pwomiiIL._AC_US218_.jpg","description":null,"brand":"","detail_url":"https://www.amazon.com/dp/B01LZVTM35","query":"xbox 360 video games ","query_group_id":0,"category":"Video Games"},{"adId":14,"campaignId":8091,"keyWords":["xbox+360+video+games+"],"relevanceScore":0.0,"pClick":0.0,"bidPrice":4.5,"rankScore":0.0,"qualityScore":0.0,"costPerClick":0.0,"position":0,"title":"Bully: Scholarship Edition - Xbox 360","price":18.99,"thumbnail":"https://images-na.ssl-images-amazon.com/images/I/51QkHsYkuHL._AC_US218_.jpg","description":null,"brand":"","detail_url":"https://www.amazon.com/dp/B01MR49GDU","query":"xbox 360 video games ","query_group_id":0,"category":"Video Games"},{"adId":14,"campaignId":8091,"keyWords":["xbox+360+video+games+"],"relevanceScore":0.0,"pClick":0.0,"bidPrice":4.5,"rankScore":0.0,"qualityScore":0.0,"costPerClick":0.0,"position":0,"title":"LEGO Marvel's Avengers - Xbox 360","price":17.65,"thumbnail":"https://images-na.ssl-images-amazon.com/images/I/518KWhloh4L._AC_US218_.jpg","description":null,"brand":"","detail_url":"https://www.amazon.com/dp/B00T57U7V6","query":"xbox 360 video games ","query_group_id":0,"category":"Video Games"},{"adId":14,"campaignId":8091,"keyWords":["xbox+360+video+games+"],"relevanceScore":0.0,"pClick":0.0,"bidPrice":4.5,"rankScore":0.0,"qualityScore":0.0,"costPerClick":0.0,"position":0,"title":"WWE 2K17 - Xbox 360","price":19.5,"thumbnail":"https://images-na.ssl-images-amazon.com/images/I/51-6RIbFprL._AC_US218_.jpg","description":"... champion of fighting video games! Get ready to be taken to ...","brand":"","detail_url":"https://www.amazon.com/dp/B01GD4923C","query":"xbox 360 video games ","query_group_id":0,"category":"Video Games"},{"adId":14,"campaignId":8091,"keyWords":["xbox+360+video+games+"],"relevanceScore":0.0,"pClick":0.0,"bidPrice":4.5,"rankScore":0.0,"qualityScore":0.0,"costPerClick":0.0,"position":0,"title":"E-rainbow 250GB 250G Internal HDD Hard Drive Disk Disc for Xbox360 XBOX 360 E S Slim Games,best gift for video game","price":25.28,"thumbnail":"https://images-na.ssl-images-amazon.com/images/I/318ZvxGqElL._AC_US218_.jpg","description":null,"brand":"Howay","detail_url":"https://www.amazon.com/dp/B00H3CBZQQ","query":"xbox 360 video games ","query_group_id":0,"category":"Video Games"},{"adId":14,"campaignId":8091,"keyWords":["xbox+360+video+games+"],"relevanceScore":0.0,"pClick":0.0,"bidPrice":4.5,"rankScore":0.0,"qualityScore":0.0,"costPerClick":0.0,"position":0,"title":"AmazonBasics High-Speed HDMI Cable - 10 Feet (2-Pack) (Latest Standard)","price":9.33,"thumbnail":"https://images-na.ssl-images-amazon.com/images/I/41pfNwgZE8L._AC_US218_.jpg","description":null,"brand":"AmazonBasics","detail_url":"https://www.amazon.com/dp/B014I8T4MO","query":"xbox 360 video games ","query_group_id":0,"category":"Video Games"},{"adId":14,"campaignId":8091,"keyWords":["xbox+360+video+games+"],"relevanceScore":0.0,"pClick":0.0,"bidPrice":4.5,"rankScore":0.0,"qualityScore":0.0,"costPerClick":0.0,"position":0,"title":"Original Microsoft Xbox 360 Power Supply AC Adapter 203W","price":34.21,"thumbnail":"https://images-na.ssl-images-amazon.com/images/I/41FXj39lM6L._AC_US218_.jpg","description":null,"brand":"HongLei","detail_url":"https://www.amazon.com/dp/B001MNTVNQ","query":"xbox 360 video games ","query_group_id":0,"category":"Video Games"},{"adId":14,"campaignId":8091,"keyWords":["xbox+360+video+games+"],"relevanceScore":0.0,"pClick":0.0,"bidPrice":4.5,"rankScore":0.0,"qualityScore":0.0,"costPerClick":0.0,"position":0,"title":"Two Black Xbox Controllers","price":19.99,"thumbnail":"https://images-na.ssl-images-amazon.com/images/I/51MJIFNvYPL._AC_US218_.jpg","description":null,"brand":"","detail_url":"https://www.amazon.com/dp/B0016CQ0Q4","query":"xbox 360 video games ","query_group_id":0,"category":"Video Games"},{"adId":14,"campaignId":8091,"keyWords":["xbox+360+video+games+"],"relevanceScore":0.0,"pClick":0.0,"bidPrice":4.5,"rankScore":0.0,"qualityScore":0.0,"costPerClick":0.0,"position":0,"title":"Bonacell 2 Pack Rechargeable Ni-MH 2200mAh Controller Replacement Battery and Charing Kit for Xbox 360 Controller","price":18.99,"thumbnail":"https://images-na.ssl-images-amazon.com/images/I/41zscNrSsrL._AC_US218_.jpg","description":null,"brand":"Bonacell","detail_url":"https://www.amazon.com/dp/B01N90W586","query":"xbox 360 video games ","query_group_id":0,"category":"Video Games"},{"adId":14,"campaignId":8091,"keyWords":["xbox+360+video+games+"],"relevanceScore":0.0,"pClick":0.0,"bidPrice":4.5,"rankScore":0.0,"qualityScore":0.0,"costPerClick":0.0,"position":0,"title":"Xbox 360 SmartGlass","price":0.0,"thumbnail":"https://images-na.ssl-images-amazon.com/images/I/41OUA7B5J1L._AC_US218_.png","description":null,"brand":"","detail_url":"https://www.amazon.com/dp/B00CF5LBYW","query":"xbox 360 video games ","query_group_id":0,"category":"Video Games"},{"adId":14,"campaignId":8091,"keyWords":["xbox+360+video+games+"],"relevanceScore":0.0,"pClick":0.0,"bidPrice":4.5,"rankScore":0.0,"qualityScore":0.0,"costPerClick":0.0,"position":0,"title":"Mafia II","price":17.99,"thumbnail":"https://images-na.ssl-images-amazon.com/images/I/513O6PjSa4L._AC_US218_.jpg","description":"... true evolutionof the Mafia game that defined a genre. Gunfights ...","brand":"","detail_url":"https://www.amazon.com/dp/B000ZK698C","query":"xbox 360 video games ","query_group_id":0,"category":"Video Games"},{"adId":14,"campaignId":8091,"keyWords":["xbox+360+video+games+"],"relevanceScore":0.0,"pClick":0.0,"bidPrice":4.5,"rankScore":0.0,"qualityScore":0.0,"costPerClick":0.0,"position":0,"title":"Tom Clancy's Ghost Recon: Future Soldier - Xbox 360","price":6.95,"thumbnail":"https://images-na.ssl-images-amazon.com/images/I/51oDF9uKhGL._AC_US218_.jpg","description":"... Intense Multiplayer - 4 game modes, 10 maps and multiple classes along ...","brand":"","detail_url":"https://www.amazon.com/dp/B0037LTTRO","query":"xbox 360 video games ","query_group_id":0,"category":"Video Games"},{"adId":14,"campaignId":8091,"keyWords":["xbox+360+video+games+"],"relevanceScore":0.0,"pClick":0.0,"bidPrice":4.5,"rankScore":0.0,"qualityScore":0.0,"costPerClick":0.0,"position":0,"title":"360 Tony Hawk Ride - Game Only - No Skat","price":9.95,"thumbnail":"https://images-na.ssl-images-amazon.com/images/I/317aBJkfhJL._AC_US218_.jpg","description":null,"brand":"","detail_url":"https://www.amazon.com/dp/B00AW1LIIU","query":"xbox 360 video games ","query_group_id":0,"category":"Video Games"},{"adId":14,"campaignId":8091,"keyWords":["xbox+360+video+games+"],"relevanceScore":0.0,"pClick":0.0,"bidPrice":4.5,"rankScore":0.0,"qualityScore":0.0,"costPerClick":0.0,"position":0,"title":"Middle Earth: Shadow of Mordor - Xbox 360","price":19.99,"thumbnail":"https://images-na.ssl-images-amazon.com/images/I/51e+ePHwvrL._AC_US218_.jpg","description":null,"brand":"","detail_url":"https://www.amazon.com/dp/B00GMFKYH6","query":"xbox 360 video games ","query_group_id":0,"category":"Video Games"},{"adId":14,"campaignId":8091,"keyWords":["xbox+360+video+games+"],"relevanceScore":0.0,"pClick":0.0,"bidPrice":4.5,"rankScore":0.0,"qualityScore":0.0,"costPerClick":0.0,"position":0,"title":"Just Dance 2017 - Xbox 360","price":24.09,"thumbnail":"https://images-na.ssl-images-amazon.com/images/I/61yWZ5bj5RL._AC_US218_.jpg","description":"Just Dance 2017 for Xbox 360 is the newest version of the world's #1 dance game","brand":"","detail_url":"https://www.amazon.com/dp/B01GWGX7TG","query":"xbox 360 video games ","query_group_id":0,"category":"Video Games"},{"adId":14,"campaignId":8091,"keyWords":["xbox+360+video+games+"],"relevanceScore":0.0,"pClick":0.0,"bidPrice":4.5,"rankScore":0.0,"qualityScore":0.0,"costPerClick":0.0,"position":0,"title":"Proxelle Video Game Chair, Dual 3W Speakers (PS4/PS3/PS2 Xbox One/Xbox 360/Nintendo Wii) Connect through TV, DVD, iPod, iPhone Android and MP3.","price":89.99,"thumbnail":"https://images-na.ssl-images-amazon.com/images/I/41arkYXHg9L._AC_US218_.jpg","description":null,"brand":"Proxelle","detail_url":"https://www.amazon.com/dp/B01EUFHFJY","query":"xbox 360 video games ","query_group_id":0,"category":"Video Games"},{"adId":14,"campaignId":8091,"keyWords":["xbox+360+video+games+"],"relevanceScore":0.0,"pClick":0.0,"bidPrice":4.5,"rankScore":0.0,"qualityScore":0.0,"costPerClick":0.0,"position":0,"title":"Teenage Mutant Ninja Turtles: Mutants in Manhattan - Xbox 360","price":12.99,"thumbnail":"https://images-na.ssl-images-amazon.com/images/I/51dQ6lI7+NL._AC_US218_.jpg","description":"... Experience the game in a whole new way when you assemble your team in 4 ...","brand":"","detail_url":"https://www.amazon.com/dp/B01B298Q8K","query":"xbox 360 video games ","query_group_id":0,"category":"Video Games"},{"adId":14,"campaignId":8091,"keyWords":["xbox+360+video+games+"],"relevanceScore":0.0,"pClick":0.0,"bidPrice":4.5,"rankScore":0.0,"qualityScore":0.0,"costPerClick":0.0,"position":0,"title":"DuckTales - Remastered 360 - Xbox 360","price":17.99,"thumbnail":"https://images-na.ssl-images-amazon.com/images/I/51CuFOuVRTL._AC_US218_.jpg","description":null,"brand":"","detail_url":"https://www.amazon.com/dp/B00F9MZT2I","query":"xbox 360 video games ","query_group_id":0,"category":"Video Games"},{"adId":14,"campaignId":8091,"keyWords":["xbox+360+video+games+"],"relevanceScore":0.0,"pClick":0.0,"bidPrice":4.5,"rankScore":0.0,"qualityScore":0.0,"costPerClick":0.0,"position":0,"title":"LEGO Harry Potter: Years 1-4 - Xbox 360","price":11.99,"thumbnail":"https://images-na.ssl-images-amazon.com/images/I/51o+LLx5Q7L._AC_US218_.jpg","description":"... moments through the proven prism of the LEGO video game franchise. ...","brand":"","detail_url":"https://www.amazon.com/dp/B002BS4JDS","query":"xbox 360 video games ","query_group_id":0,"category":"Video Games"},{"adId":14,"campaignId":8091,"keyWords":["xbox+360+video+games+"],"relevanceScore":0.0,"pClick":0.0,"bidPrice":4.5,"rankScore":0.0,"qualityScore":0.0,"costPerClick":0.0,"position":0,"title":"Madden NFL 16 - Xbox 360","price":12.99,"thumbnail":"https://images-na.ssl-images-amazon.com/images/I/51REp5hZMkL._AC_US218_.jpg","description":null,"brand":"","detail_url":"https://www.amazon.com/dp/B00W435CPY","query":"xbox 360 video games ","query_group_id":0,"category":"Video Games"},{"adId":14,"campaignId":8091,"keyWords":["xbox+360+video+games+"],"relevanceScore":0.0,"pClick":0.0,"bidPrice":4.5,"rankScore":0.0,"qualityScore":0.0,"costPerClick":0.0,"position":0,"title":"Your Shape Fitness Evolved - Xbox 360","price":0.0,"thumbnail":"https://images-na.ssl-images-amazon.com/images/I/51gcyDU9V+L._AC_US218_.jpg","description":null,"brand":"","detail_url":"https://www.amazon.com/dp/B002I0H9WM","query":"xbox 360 video games ","query_group_id":0,"category":"Video Games"},{"adId":14,"campaignId":8091,"keyWords":["xbox+360+video+games+"],"relevanceScore":0.0,"pClick":0.0,"bidPrice":4.5,"rankScore":0.0,"qualityScore":0.0,"costPerClick":0.0,"position":0,"title":"Batman: Arkham Origins - Xbox 360","price":12.92,"thumbnail":"https://images-na.ssl-images-amazon.com/images/I/51qBYOURUSL._AC_US218_.jpg","description":"Publisher: Warner Bros ; Platform: Xbox 360","brand":"","detail_url":"https://www.amazon.com/dp/B00C71034I","query":"xbox 360 video games ","query_group_id":0,"category":"Video Games"},{"adId":14,"campaignId":8091,"keyWords":["xbox+360+video+games+"],"relevanceScore":0.0,"pClick":0.0,"bidPrice":4.5,"rankScore":0.0,"qualityScore":0.0,"costPerClick":0.0,"position":0,"title":"HALO 3 (XBOX 360) by BUNGIE","price":14.99,"thumbnail":"https://images-na.ssl-images-amazon.com/images/I/51j-b-7yN7L._AC_US218_.jpg","description":null,"brand":"","detail_url":"https://www.amazon.com/dp/B00361YT9I","query":"xbox 360 video games ","query_group_id":0,"category":"Video Games"},{"adId":14,"campaignId":8091,"keyWords":["xbox+360+video+games+"],"relevanceScore":0.0,"pClick":0.0,"bidPrice":4.5,"rankScore":0.0,"qualityScore":0.0,"costPerClick":0.0,"position":0,"title":"GENUINE Official Microsoft Xbox 360 Power Supply AC Adapter 203W 12V-14.2A","price":34.21,"thumbnail":"https://images-na.ssl-images-amazon.com/images/I/51iHUCL4rpL._AC_US218_.jpg","description":null,"brand":"HongLei","detail_url":"https://www.amazon.com/dp/B00XGNOBDA","query":"xbox 360 video games ","query_group_id":0,"category":"Video Games"},{"adId":14,"campaignId":8091,"keyWords":["xbox+360+video+games+"],"relevanceScore":0.0,"pClick":0.0,"bidPrice":4.5,"rankScore":0.0,"qualityScore":0.0,"costPerClick":0.0,"position":0,"title":"Deadpool - Xbox 360","price":12.31,"thumbnail":"https://images-na.ssl-images-amazon.com/images/I/51z-G9ihCiL._AC_US218_.jpg","description":"... all my good sides, so I made my game a third-person, action-shooter. ...","brand":"","detail_url":"https://www.amazon.com/dp/B008LW4SBQ","query":"xbox 360 video games ","query_group_id":0,"category":"Video Games"},{"adId":14,"campaignId":8091,"keyWords":["xbox+360+video+games+"],"relevanceScore":0.0,"pClick":0.0,"bidPrice":4.5,"rankScore":0.0,"qualityScore":0.0,"costPerClick":0.0,"position":0,"title":"Scarface: The World Is Yours - Xbox","price":94.99,"thumbnail":"https://images-na.ssl-images-amazon.com/images/I/412K7HZVXHL._AC_US218_.jpg","description":null,"brand":"","detail_url":"https://www.amazon.com/dp/B0007PLKZW","query":"xbox 360 video games ","query_group_id":0,"category":"Video Games"},{"adId":14,"campaignId":8091,"keyWords":["xbox+360+video+games+"],"relevanceScore":0.0,"pClick":0.0,"bidPrice":4.5,"rankScore":0.0,"qualityScore":0.0,"costPerClick":0.0,"position":0,"title":"World of Tanks - Xbox 360 Edition","price":0.0,"thumbnail":"https://images-na.ssl-images-amazon.com/images/I/51R4dIlipYL._AC_US218_.jpg","description":"World of Tanks-X360 Xbox 360 English US NTSC DVD - Xbox 360","brand":"Microsoft","detail_url":"https://www.amazon.com/dp/B00J9C260M","query":"xbox 360 video games ","query_group_id":0,"category":"Video Games"},{"adId":14,"campaignId":8091,"keyWords":["xbox+360+video+games+"],"relevanceScore":0.0,"pClick":0.0,"bidPrice":4.5,"rankScore":0.0,"qualityScore":0.0,"costPerClick":0.0,"position":0,"title":"DanTDM Daniel Middleton autographed Video Game Cover XBox 360 Minecraft The Diamond Minecart","price":69.95,"thumbnail":"https://images-na.ssl-images-amazon.com/images/I/51pM3rvMOuL._AC_US218_.jpg","description":"... Middleton autographed Video Game Cover for XBox 360 Minecraft was signed ...","brand":"The Diamond Minecart","detail_url":"https://www.amazon.com/dp/B0739PRZ75","query":"xbox 360 video games ","query_group_id":0,"category":"Video Games"},{"adId":14,"campaignId":8091,"keyWords":["xbox+360+video+games+"],"relevanceScore":0.0,"pClick":0.0,"bidPrice":4.5,"rankScore":0.0,"qualityScore":0.0,"costPerClick":0.0,"position":0,"title":"Destiny: The Taken King - Legendary Edition - Xbox 360","price":18.49,"thumbnail":"https://images-na.ssl-images-amazon.com/images/I/51-4IOnjqvL._AC_US218_.jpg","description":"... Contents include: Destiny Base Game, Expansion I, Expansion II, and The ...","brand":"","detail_url":"https://www.amazon.com/dp/B00ZJ20YTG","query":"xbox 360 video games ","query_group_id":0,"category":"Video Games"},{"adId":14,"campaignId":8091,"keyWords":["xbox+360+video+games+"],"relevanceScore":0.0,"pClick":0.0,"bidPrice":4.5,"rankScore":0.0,"qualityScore":0.0,"costPerClick":0.0,"position":0,"title":"Nyko Charge Base 360 S for Xbox 360","price":16.79,"thumbnail":"https://images-na.ssl-images-amazon.com/images/I/41n+GGdSO8L._AC_US218_.jpg","description":null,"brand":"","detail_url":"https://www.amazon.com/dp/B00273Z9WM","query":"xbox 360 video games ","query_group_id":0,"category":"Video Games"},{"adId":14,"campaignId":8091,"keyWords":["xbox+360+video+games+"],"relevanceScore":0.0,"pClick":0.0,"bidPrice":4.5,"rankScore":0.0,"qualityScore":0.0,"costPerClick":0.0,"position":0,"title":"Transformers: The Game","price":0.0,"thumbnail":"https://images-na.ssl-images-amazon.com/images/I/51KhnsH3txL._AC_US218_.jpg","description":null,"brand":"","detail_url":"https://www.amazon.com/dp/B001AE5STI","query":"xbox 360 video games ","query_group_id":0,"category":"Video Games"},{"adId":14,"campaignId":8091,"keyWords":["xbox+360+video+games+"],"relevanceScore":0.0,"pClick":0.0,"bidPrice":4.5,"rankScore":0.0,"qualityScore":0.0,"costPerClick":0.0,"position":0,"title":"B&A \"Controlling\" Funny Video Game Controller & TV Remote Arguing - Vinyl Sticker","price":7.99,"thumbnail":"https://images-na.ssl-images-amazon.com/images/I/41Bu2eXHIJL._AC_US218_.jpg","description":null,"brand":"B&A","detail_url":"https://www.amazon.com/dp/B00K6KTWXK","query":"xbox 360 video games ","query_group_id":0,"category":"Video Games"},{"adId":14,"campaignId":8091,"keyWords":["xbox+360+video+games+"],"relevanceScore":0.0,"pClick":0.0,"bidPrice":4.5,"rankScore":0.0,"qualityScore":0.0,"costPerClick":0.0,"position":0,"title":"GAEMS Universal M155-Console Backpack for PS4, XBOX ONE, PS3, Xbox 360","price":28.79,"thumbnail":"https://images-na.ssl-images-amazon.com/images/I/31JffWSEq-L._AC_US218_.jpg","description":null,"brand":"","detail_url":"https://www.amazon.com/dp/B010GI8PKW","query":"xbox 360 video games ","query_group_id":0,"category":"Video Games"},{"adId":14,"campaignId":8091,"keyWords":["xbox+360+video+games+"],"relevanceScore":0.0,"pClick":0.0,"bidPrice":4.5,"rankScore":0.0,"qualityScore":0.0,"costPerClick":0.0,"position":0,"title":"Rage","price":9.99,"thumbnail":"https://images-na.ssl-images-amazon.com/images/I/51rWhiddjrL._AC_US218_.jpg","description":"... 4/2011 PLATFORMS: Xbox 360™ / PLAYSTATION®3 / Games for Windows GENRE ...","brand":"","detail_url":"https://www.amazon.com/dp/B00354NAYG","query":"xbox 360 video games ","query_group_id":0,"category":"Video Games"},{"adId":14,"campaignId":8091,"keyWords":["xbox+360+video+games+"],"relevanceScore":0.0,"pClick":0.0,"bidPrice":4.5,"rankScore":0.0,"qualityScore":0.0,"costPerClick":0.0,"position":0,"title":"XBOX 360 KINECT ADVENTURES - BRAND NEW & SEALED!","price":2.99,"thumbnail":"https://images-na.ssl-images-amazon.com/images/I/51fx4iYTRpL._AC_US218_.jpg","description":"XBOX 360 Kinetc Adventures","brand":"NOT APPLICABLE","detail_url":"https://www.amazon.com/dp/B01MSVM1IM","query":"xbox 360 video games ","query_group_id":0,"category":"Video Games"},{"adId":14,"campaignId":8091,"keyWords":["xbox+360+video+games+"],"relevanceScore":0.0,"pClick":0.0,"bidPrice":4.5,"rankScore":0.0,"qualityScore":0.0,"costPerClick":0.0,"position":0,"title":"Cabela's Dangerous Hunts 2013 - Xbox 360","price":9.35,"thumbnail":"https://images-na.ssl-images-amazon.com/images/I/61yK9nQylpL._AC_US218_.jpg","description":null,"brand":"","detail_url":"https://www.amazon.com/dp/B008HHTDP6","query":"xbox 360 video games ","query_group_id":0,"category":"Video Games"},{"adId":14,"campaignId":8091,"keyWords":["xbox+360+video+games+"],"relevanceScore":0.0,"pClick":0.0,"bidPrice":4.5,"rankScore":0.0,"qualityScore":0.0,"costPerClick":0.0,"position":0,"title":"Sonic & Sega All-Stars Racing","price":15.79,"thumbnail":"https://images-na.ssl-images-amazon.com/images/I/61BXpzQdtwL._AC_US218_.jpg","description":"Sonic & Sega All-Stars Racing Xbox 360","brand":"","detail_url":"https://www.amazon.com/dp/B002BRYHUY","query":"xbox 360 video games ","query_group_id":0,"category":"Video Games"}]