[{"adId":16,"campaignId":8115,"keyWords":["glass+office+desk+"],"relevanceScore":0.0,"pClick":0.0,"bidPrice":20.0,"rankScore":0.0,"qualityScore":0.0,"costPerClick":0.0,"position":0,"title":"Naomi Home 3 Piece Allison Glass Office Desk White","price":129.0,"thumbnail":"https://images-na.ssl-images-amazon.com/images/I/51-rhzK5-NL._AC_US218_.jpg","description":null,"brand":"Naomi Home","detail_url":"https://www.amazon.com/dp/B07234CVGS","query":"glass office desk ","query_group_id":0,"category":"Home & Kitchen"},{"adId":16,"campaignId":8115,"keyWords":["glass+office+desk+"],"relevanceScore":0.0,"pClick":0.0,"bidPrice":20.0,"rankScore":0.0,"qualityScore":0.0,"costPerClick":0.0,"position":0,"title":"Z-Line Belaire Glass L-Shaped Computer Desk","price":99.15,"thumbnail":"https://images-na.ssl-images-amazon.com/images/I/41W4EVeHl1L._AC_US218_.jpg","description":null,"brand":"Z-Line Designs","detail_url":"https://www.amazon.com/dp/B0019MAUTE","query":"glass office desk ","query_group_id":0,"category":"Home & Kitchen"},{"adId":16,"campaignId":8115,"keyWords":["glass+office+desk+"],"relevanceScore":0.0,"pClick":0.0,"bidPrice":20.0,"rankScore":0.0,"qualityScore":0.0,"costPerClick":0.0,"position":0,"title":"Tempered Glass L Shape Corner Desk With Pull Out Keybaord Panel. Color: Clear","price":88.84,"thumbnail":"https://images-na.ssl-images-amazon.com/images/I/419s7EZw3NL._AC_US218_.jpg","description":null,"brand":"Techni Mobili","detail_url":"https://www.amazon.com/dp/B003FSTNBQ","query":"glass office desk ","query_group_id":0,"category":"Home & Kitchen"},{"adId":16,"campaignId":8115,"keyWords":["glass+office+desk+"],"relevanceScore":0.0,"pClick":0.0,"bidPrice":20.0,"rankScore":0.0,"qualityScore":0.0,"costPerClick":0.0,"position":0,"title":"Signature Design by Ashley H410-24 Baraga Collection Home Office Desk, 61\", White","price":175.03,"thumbnail":"https://images-na.ssl-images-amazon.com/images/I/31fCvx4TPgL._AC_US218_.jpg","description":null,"brand":"Signature Design by Ashley","detail_url":"https://www.amazon.com/dp/B00EUT6LX2","query":"glass office desk ","query_group_id":0,"category":"Home & Kitchen"},{"adId":16,"campaignId":8115,"keyWords":["glass+office+desk+"],"relevanceScore":0.0,"pClick":0.0,"bidPrice":20.0,"rankScore":0.0,"qualityScore":0.0,"costPerClick":0.0,"position":0,"title":"Coaster Furniture Computer Desk with Glass Top","price":0.0,"thumbnail":"https://images-na.ssl-images-amazon.com/images/I/510qsCxT-JL._AC_US218_.jpg","description":null,"brand":"Coaster Home Furnishings","detail_url":"https://www.amazon.com/dp/B01N45TMG8","query":"glass office desk ","query_group_id":0,"category":"Home & Kitchen"},{"adId":16,"campaignId":8115,"keyWords":["glass+office+desk+"],"relevanceScore":0.0,"pClick":0.0,"bidPrice":20.0,"rankScore":0.0,"qualityScore":0.0,"costPerClick":0.0,"position":0,"title":"Glass Computer Desk w/ Pull-Out Keyboard Tray","price":92.18,"thumbnail":"https://images-na.ssl-images-amazon.com/images/I/41qMfecdsjL._AC_US218_.jpg","description":null,"brand":"Flash Furniture","detail_url":"https://www.amazon.com/dp/B00BK31NDY","query":"glass office desk ","query_group_id":0,"category":"Home & Kitchen"},{"adId":16,"campaignId":8115,"keyWords":["glass+office+desk+"],"relevanceScore":0.0,"pClick":0.0,"bidPrice":20.0,"rankScore":0.0,"qualityScore":0.0,"costPerClick":0.0,"position":0,"title":"Glass L-Shape Computer Desk with Silver Frame Finish","price":83.99,"thumbnail":"https://images-na.ssl-images-amazon.com/images/I/41Jg97SexuL._AC_US218_.jpg","description":null,"brand":"Flash Furniture","detail_url":"https://www.amazon.com/dp/B00VTQSHPE","query":"glass office desk ","query_group_id":0,"category":"Home & Kitchen"},{"adId":16,"campaignId":8115,"keyWords":["glass+office+desk+"],"relevanceScore":0.0,"pClick":0.0,"bidPrice":20.0,"rankScore":0.0,"qualityScore":0.0,"costPerClick":0.0,"position":0,"title":"WE Furniture Elite Soreno Glass Corner Computer Desk, Black","price":88.75,"thumbnail":"https://images-na.ssl-images-amazon.com/images/I/51HhQH33NlL._AC_US218_.jpg","description":null,"brand":"WE Furniture","detail_url":"https://www.amazon.com/dp/B015MJHWSQ","query":"glass office desk ","query_group_id":0,"category":"Home & Kitchen"},{"adId":16,"campaignId":8115,"keyWords":["glass+office+desk+"],"relevanceScore":0.0,"pClick":0.0,"bidPrice":20.0,"rankScore":0.0,"qualityScore":0.0,"costPerClick":0.0,"position":0,"title":"Whalen Furniture JCS110605-D Newport Wood/Glass L-Shaped Desk","price":132.74,"thumbnail":"https://images-na.ssl-images-amazon.com/images/I/41a45xNJV9L._AC_US218_.jpg","description":null,"brand":"Whalen Furniture","detail_url":"https://www.amazon.com/dp/B00FSE7GN2","query":"glass office desk ","query_group_id":0,"category":"Home & Kitchen"},{"adId":16,"campaignId":8115,"keyWords":["glass+office+desk+"],"relevanceScore":0.0,"pClick":0.0,"bidPrice":20.0,"rankScore":0.0,"qualityScore":0.0,"costPerClick":0.0,"position":0,"title":"Walker Edison Soreno 3-Piece Corner Desk, Black with Black Glass","price":125.19,"thumbnail":"https://images-na.ssl-images-amazon.com/images/I/41E6hJc1stL._AC_US218_.jpg","description":null,"brand":"Walker Edison Furniture Company","detail_url":"https://www.amazon.com/dp/B001FB5LE8","query":"glass office desk ","query_group_id":0,"category":"Home & Kitchen"},{"adId":16,"campaignId":8115,"keyWords":["glass+office+desk+"],"relevanceScore":0.0,"pClick":0.0,"bidPrice":20.0,"rankScore":0.0,"qualityScore":0.0,"costPerClick":0.0,"position":0,"title":"Merax Home Office Computer Desk Simple Design Table Workstation with Glass Top (Black)","price":91.76,"thumbnail":"https://images-na.ssl-images-amazon.com/images/I/41nNIYkBX8L._AC_US218_.jpg","description":null,"brand":"Merax","detail_url":"https://www.amazon.com/dp/B0711QDNJF","query":"glass office desk ","query_group_id":0,"category":"Home & Kitchen"},{"adId":16,"campaignId":8115,"keyWords":["glass+office+desk+"],"relevanceScore":0.0,"pClick":0.0,"bidPrice":20.0,"rankScore":0.0,"qualityScore":0.0,"costPerClick":0.0,"position":0,"title":"Coaster L-Shape Home Office Computer Desk, Cappuccino Finish Base, Glass Top","price":249.64,"thumbnail":"https://images-na.ssl-images-amazon.com/images/I/51-O0W4RvOL._AC_US218_.jpg","description":null,"brand":"Coaster Home Furnishings","detail_url":"https://www.amazon.com/dp/B001HFB6MS","query":"glass office desk ","query_group_id":0,"category":"Home & Kitchen"},{"adId":16,"campaignId":8115,"keyWords":["glass+office+desk+"],"relevanceScore":0.0,"pClick":0.0,"bidPrice":20.0,"rankScore":0.0,"qualityScore":0.0,"costPerClick":0.0,"position":0,"title":"Creative Images International Glass Collection Bent Glass Office Desk, Clear","price":384.69,"thumbnail":"https://images-na.ssl-images-amazon.com/images/I/31crSnVGatL._AC_US218_.jpg","description":null,"brand":"Neos Modern Furniture","detail_url":"https://www.amazon.com/dp/B01DDOXS94","query":"glass office desk ","query_group_id":0,"category":"Home & Kitchen"},{"adId":16,"campaignId":8115,"keyWords":["glass+office+desk+"],"relevanceScore":0.0,"pClick":0.0,"bidPrice":20.0,"rankScore":0.0,"qualityScore":0.0,"costPerClick":0.0,"position":0,"title":"Black Metal Glass Corner Computer Desk","price":104.55,"thumbnail":"https://images-na.ssl-images-amazon.com/images/I/61Dov9GQmvL._AC_US218_.jpg","description":null,"brand":"WE Furniture","detail_url":"https://www.amazon.com/dp/B00CAO6JTU","query":"glass office desk ","query_group_id":0,"category":"Home & Kitchen"},{"adId":16,"campaignId":8115,"keyWords":["glass+office+desk+"],"relevanceScore":0.0,"pClick":0.0,"bidPrice":20.0,"rankScore":0.0,"qualityScore":0.0,"costPerClick":0.0,"position":0,"title":"Coaster 800818 Home Furnishings Desk, Weathered Grey","price":173.26,"thumbnail":"https://images-na.ssl-images-amazon.com/images/I/41hZy5rZjfL._AC_US218_.jpg","description":null,"brand":"Coaster Home Furnishings","detail_url":"https://www.amazon.com/dp/B015HSXBGO","query":"glass office desk ","query_group_id":0,"category":"Home & Kitchen"},{"adId":16,"campaignId":8115,"keyWords":["glass+office+desk+"],"relevanceScore":0.0,"pClick":0.0,"bidPrice":20.0,"rankScore":0.0,"qualityScore":0.0,"costPerClick":0.0,"position":0,"title":"Monarch Computer Desk, Glossy White, 48\"","price":197.25,"thumbnail":"https://images-na.ssl-images-amazon.com/images/I/31Msxxhxj5L._AC_US218_.jpg","description":null,"brand":"Monarch","detail_url":"https://www.amazon.com/dp/B0195C0NXM","query":"glass office desk ","query_group_id":0,"category":"Home & Kitchen"},{"adId":16,"campaignId":8115,"keyWords":["glass+office+desk+"],"relevanceScore":0.0,"pClick":0.0,"bidPrice":20.0,"rankScore":0.0,"qualityScore":0.0,"costPerClick":0.0,"position":0,"title":"Target Marketing Systems World Map Desk with a Clear Tempered Glass Top, Silver","price":117.79,"thumbnail":"https://images-na.ssl-images-amazon.com/images/I/41AEjY2tl+L._AC_US218_.jpg","description":null,"brand":"Target Marketing Systems","detail_url":"https://www.amazon.com/dp/B00FRGFE44","query":"glass office desk ","query_group_id":0,"category":"Home & Kitchen"},{"adId":16,"campaignId":8115,"keyWords":["glass+office+desk+"],"relevanceScore":0.0,"pClick":0.0,"bidPrice":20.0,"rankScore":0.0,"qualityScore":0.0,"costPerClick":0.0,"position":0,"title":"Bonvivo Designer Desk Massimo, Modern Secretary In A Contemporary Design","price":179.9,"thumbnail":"https://images-na.ssl-images-amazon.com/images/I/41CdSPiMFGL._AC_US218_.jpg","description":null,"brand":"bonVIVO","detail_url":"https://www.amazon.com/dp/B01K4I1SPI","query":"glass office desk ","query_group_id":0,"category":"Home & Kitchen"},{"adId":16,"campaignId":8115,"keyWords":["glass+office+desk+"],"relevanceScore":0.0,"pClick":0.0,"bidPrice":20.0,"rankScore":0.0,"qualityScore":0.0,"costPerClick":0.0,"position":0,"title":"Dland Luxurious Computer Desk 47\" Large Size Home Office Decent PC Laptop Desk Studying Writing Table Modern Workstation, Teak","price":99.0,"thumbnail":"https://images-na.ssl-images-amazon.com/images/I/41qEzIXNhAL._AC_US218_.jpg","description":null,"brand":"Dland","detail_url":"https://www.amazon.com/dp/B0722V15H7","query":"glass office desk ","query_group_id":0,"category":"Home & Kitchen"},{"adId":16,"campaignId":8115,"keyWords":["glass+office+desk+"],"relevanceScore":0.0,"pClick":0.0,"bidPrice":20.0,"rankScore":0.0,"qualityScore":0.0,"costPerClick":0.0,"position":0,"title":"Standing Desk X-Elite – Stand Steady Standing Desk | X-Elite Pro Version, Instantly Convert Any Desk into a Sit / Stand up Desk, Height-Adjustable, Fully Assembled Desk Converter (Cherry)","price":199.99,"thumbnail":"https://images-na.ssl-images-amazon.com/images/I/51aWvhIFw7L._AC_US218_.jpg","description":null,"brand":"Stand Steady","detail_url":"https://www.amazon.com/dp/B01NC0I0RG","query":"glass office desk ","query_group_id":0,"category":"Home & Kitchen"},{"adId":16,"campaignId":8115,"keyWords":["glass+office+desk+"],"relevanceScore":0.0,"pClick":0.0,"bidPrice":20.0,"rankScore":0.0,"qualityScore":0.0,"costPerClick":0.0,"position":0,"title":"Tangkula Computer Desk Glass Top with Drawer Compute Desk Table Home Office Furniture","price":79.99,"thumbnail":"https://images-na.ssl-images-amazon.com/images/I/41ISOhlh9mL._AC_US218_.jpg","description":null,"brand":"Tangkula","detail_url":"https://www.amazon.com/dp/B01MXTN87L","query":"glass office desk ","query_group_id":0,"category":"Home & Kitchen"},{"adId":16,"campaignId":8115,"keyWords":["glass+office+desk+"],"relevanceScore":0.0,"pClick":0.0,"bidPrice":20.0,"rankScore":0.0,"qualityScore":0.0,"costPerClick":0.0,"position":0,"title":"Personalized Office Desk Name Plate 3/8\" Glass-like Acrylic - customized Round Top","price":20.25,"thumbnail":"https://images-na.ssl-images-amazon.com/images/I/41JtMS60M2L._AC_US218_.jpg","description":null,"brand":"Engravers Central","detail_url":"https://www.amazon.com/dp/B01JXNX4G6","query":"glass office desk ","query_group_id":0,"category":"Home & Kitchen"},{"adId":16,"campaignId":8115,"keyWords":["glass+office+desk+"],"relevanceScore":0.0,"pClick":0.0,"bidPrice":20.0,"rankScore":0.0,"qualityScore":0.0,"costPerClick":0.0,"position":0,"title":"Best Choice Products L-Shape Computer Desk PC Glass Laptop Table Workstation Corner Home Office White","price":109.99,"thumbnail":"https://images-na.ssl-images-amazon.com/images/I/61SJ7sDrR6L._AC_US218_.jpg","description":null,"brand":"Best Choice Products","detail_url":"https://www.amazon.com/dp/B01GWCTWV2","query":"glass office desk ","query_group_id":0,"category":"Home & Kitchen"},{"adId":16,"campaignId":8115,"keyWords":["glass+office+desk+"],"relevanceScore":0.0,"pClick":0.0,"bidPrice":20.0,"rankScore":0.0,"qualityScore":0.0,"costPerClick":0.0,"position":0,"title":"VECELO L-Shape Corner Computer Desk - Transparent","price":75.99,"thumbnail":"https://images-na.ssl-images-amazon.com/images/I/51flQ1haYgL._AC_US218_.jpg","description":null,"brand":"VECELO","detail_url":"https://www.amazon.com/dp/B01GCM0388","query":"glass office desk ","query_group_id":0,"category":"Home & Kitchen"},{"adId":16,"campaignId":8115,"keyWords":["glass+office+desk+"],"relevanceScore":0.0,"pClick":0.0,"bidPrice":20.0,"rankScore":0.0,"qualityScore":0.0,"costPerClick":0.0,"position":0,"title":"Z-Line Nero Desk and Bookcase","price":103.61,"thumbnail":"https://images-na.ssl-images-amazon.com/images/I/51lGP+2IFcL._AC_US218_.jpg","description":null,"brand":"Z-Line Designs","detail_url":"https://www.amazon.com/dp/B001F2CT7O","query":"glass office desk ","query_group_id":0,"category":"Home & Kitchen"},{"adId":16,"campaignId":8115,"keyWords":["glass+office+desk+"],"relevanceScore":0.0,"pClick":0.0,"bidPrice":20.0,"rankScore":0.0,"qualityScore":0.0,"costPerClick":0.0,"position":0,"title":"OFFICE MORE Corner Computer Desk Laptop Table& Student Workstation","price":69.99,"thumbnail":"https://images-na.ssl-images-amazon.com/images/I/51Y6neKRubL._AC_US218_.jpg","description":null,"brand":"OFFICE MORE","detail_url":"https://www.amazon.com/dp/B071S6YCW8","query":"glass office desk ","query_group_id":0,"category":"Home & Kitchen"},{"adId":16,"campaignId":8115,"keyWords":["glass+office+desk+"],"relevanceScore":0.0,"pClick":0.0,"bidPrice":20.0,"rankScore":0.0,"qualityScore":0.0,"costPerClick":0.0,"position":0,"title":"Soges Computer Desk 30\" Glass Desk Workstation with Glass Top Office Desk with Bookcase & Pullout Keyboard Tray","price":95.0,"thumbnail":"https://images-na.ssl-images-amazon.com/images/I/51pO1v1dbqL._AC_US218_.jpg","description":null,"brand":"soges","detail_url":"https://www.amazon.com/dp/B01MED33X2","query":"glass office desk ","query_group_id":0,"category":"Home & Kitchen"},{"adId":16,"campaignId":8115,"keyWords":["glass+office+desk+"],"relevanceScore":0.0,"pClick":0.0,"bidPrice":20.0,"rankScore":0.0,"qualityScore":0.0,"costPerClick":0.0,"position":0,"title":"Merax Home Office Computer Desk Table Workstation with Metal Cabinet and Glass Top (Black)","price":152.96,"thumbnail":"https://images-na.ssl-images-amazon.com/images/I/51+BNpbKR4L._AC_US218_.jpg","description":null,"brand":"Merax","detail_url":"https://www.amazon.com/dp/B071HQHMWX","query":"glass office desk ","query_group_id":0,"category":"Home & Kitchen"},{"adId":16,"campaignId":8115,"keyWords":["glass+office+desk+"],"relevanceScore":0.0,"pClick":0.0,"bidPrice":20.0,"rankScore":0.0,"qualityScore":0.0,"costPerClick":0.0,"position":0,"title":"Coaster Home Furnishings Contemporary Writing Desk, Chrome","price":115.45,"thumbnail":"https://images-na.ssl-images-amazon.com/images/I/51Pyrg7MR6L._AC_US218_.jpg","description":null,"brand":"Coaster Home Furnishings","detail_url":"https://www.amazon.com/dp/B00BGUPFM6","query":"glass office desk ","query_group_id":0,"category":"Home & Kitchen"},{"adId":16,"campaignId":8115,"keyWords":["glass+office+desk+"],"relevanceScore":0.0,"pClick":0.0,"bidPrice":20.0,"rankScore":0.0,"qualityScore":0.0,"costPerClick":0.0,"position":0,"title":"Coaster Home Furnishings 800804 Writing Desk, Clear Tempered Glass/Nickel","price":0.0,"thumbnail":"https://images-na.ssl-images-amazon.com/images/I/515Y6XZimuL._AC_US218_.jpg","description":null,"brand":"Coaster Home Furnishings","detail_url":"https://www.amazon.com/dp/B018FNBRXW","query":"glass office desk ","query_group_id":0,"category":"Home & Kitchen"},{"adId":16,"campaignId":8115,"keyWords":["glass+office+desk+"],"relevanceScore":0.0,"pClick":0.0,"bidPrice":20.0,"rankScore":0.0,"qualityScore":0.0,"costPerClick":0.0,"position":0,"title":"Ryan Rove Madison 3-Piece Corner L-Shaped Computer Desk in Black and Clear Glass","price":129.99,"thumbnail":"https://images-na.ssl-images-amazon.com/images/I/51QZdDF0d6L._AC_US218_.jpg","description":null,"brand":"Ryan Rove","detail_url":"https://www.amazon.com/dp/B06XJFZFG6","query":"glass office desk ","query_group_id":0,"category":"Home & Kitchen"},{"adId":16,"campaignId":8115,"keyWords":["glass+office+desk+"],"relevanceScore":0.0,"pClick":0.0,"bidPrice":20.0,"rankScore":0.0,"qualityScore":0.0,"costPerClick":0.0,"position":0,"title":"Z-Line Brisa Desk","price":0.0,"thumbnail":"https://images-na.ssl-images-amazon.com/images/I/41vc7eVD+bL._AC_US218_.jpg","description":null,"brand":"Z-Line Designs","detail_url":"https://www.amazon.com/dp/B002FYISNK","query":"glass office desk ","query_group_id":0,"category":"Home & Kitchen"},{"adId":16,"campaignId":8115,"keyWords":["glass+office+desk+"],"relevanceScore":0.0,"pClick":0.0,"bidPrice":20.0,"rankScore":0.0,"qualityScore":0.0,"costPerClick":0.0,"position":0,"title":"Cabot L Shaped Desk","price":248.0,"thumbnail":"https://images-na.ssl-images-amazon.com/images/I/41ZjTgFkviL._AC_US218_.jpg","description":null,"brand":"Bush Furniture","detail_url":"https://www.amazon.com/dp/B005EOL812","query":"glass office desk ","query_group_id":0,"category":"Home & Kitchen"},{"adId":16,"campaignId":8115,"keyWords":["glass+office+desk+"],"relevanceScore":0.0,"pClick":0.0,"bidPrice":20.0,"rankScore":0.0,"qualityScore":0.0,"costPerClick":0.0,"position":0,"title":"Flash Furniture Computer Desk with Glass Top and 3 Drawer Pedestal, White","price":200.49,"thumbnail":"https://images-na.ssl-images-amazon.com/images/I/31Qr4VfqqwL._AC_US218_.jpg","description":null,"brand":"Flash Furniture","detail_url":"https://www.amazon.com/dp/B00W8VF7UC","query":"glass office desk ","query_group_id":0,"category":"Home & Kitchen"},{"adId":16,"campaignId":8115,"keyWords":["glass+office+desk+"],"relevanceScore":0.0,"pClick":0.0,"bidPrice":20.0,"rankScore":0.0,"qualityScore":0.0,"costPerClick":0.0,"position":0,"title":"Stylish Frosted Glass Top Computer Desk with Storage. Color: Expresso","price":110.97,"thumbnail":"https://images-na.ssl-images-amazon.com/images/I/41Sw77mjHHL._AC_US218_.jpg","description":null,"brand":"Techni Mobili","detail_url":"https://www.amazon.com/dp/B003FSTNA2","query":"glass office desk ","query_group_id":0,"category":"Home & Kitchen"},{"adId":16,"campaignId":8115,"keyWords":["glass+office+desk+"],"relevanceScore":0.0,"pClick":0.0,"bidPrice":20.0,"rankScore":0.0,"qualityScore":0.0,"costPerClick":0.0,"position":0,"title":"HomCom 64\" Modern L-Shaped Glasstop Office Workstation Computer Desk - Black","price":0.0,"thumbnail":"https://images-na.ssl-images-amazon.com/images/I/41SZmtQ1ASL._AC_US218_.jpg","description":null,"brand":"HOMCOM","detail_url":"https://www.amazon.com/dp/B00P1PWN40","query":"glass office desk ","query_group_id":0,"category":"Home & Kitchen"},{"adId":16,"campaignId":8115,"keyWords":["glass+office+desk+"],"relevanceScore":0.0,"pClick":0.0,"bidPrice":20.0,"rankScore":0.0,"qualityScore":0.0,"costPerClick":0.0,"position":0,"title":"AmazonBasics High-Back Executive Chair - Black","price":109.99,"thumbnail":"https://images-na.ssl-images-amazon.com/images/I/41kID5NlwWL._AC_US218_.jpg","description":null,"brand":"AmazonBasics","detail_url":"https://www.amazon.com/dp/B00XBC3BF0","query":"glass office desk ","query_group_id":0,"category":"Home & Kitchen"},{"adId":16,"campaignId":8115,"keyWords":["glass+office+desk+"],"relevanceScore":0.0,"pClick":0.0,"bidPrice":20.0,"rankScore":0.0,"qualityScore":0.0,"costPerClick":0.0,"position":0,"title":"go2buy Tempered Glass Table Top Computer Desk Black Metal Frame/Leg Pull out Keyboard Tray Home Office Workstation","price":58.99,"thumbnail":"https://images-na.ssl-images-amazon.com/images/I/51q+wQ7P59L._AC_US218_.jpg","description":null,"brand":"Go2buy","detail_url":"https://www.amazon.com/dp/B01N9UPTZW","query":"glass office desk ","query_group_id":0,"category":"Home & Kitchen"},{"adId":16,"campaignId":8115,"keyWords":["glass+office+desk+"],"relevanceScore":0.0,"pClick":0.0,"bidPrice":20.0,"rankScore":0.0,"qualityScore":0.0,"costPerClick":0.0,"position":0,"title":"IKAYAA Modern Computer Desk PC Laptop Table Home Office Furniture, Tempered Galss Top","price":99.99,"thumbnail":"https://images-na.ssl-images-amazon.com/images/I/41jkegTEiJL._AC_US218_.jpg","description":null,"brand":"IKAYAA","detail_url":"https://www.amazon.com/dp/B01IVLJPAU","query":"glass office desk ","query_group_id":0,"category":"Home & Kitchen"},{"adId":16,"campaignId":8115,"keyWords":["glass+office+desk+"],"relevanceScore":0.0,"pClick":0.0,"bidPrice":20.0,"rankScore":0.0,"qualityScore":0.0,"costPerClick":0.0,"position":0,"title":"Desktex Anti-Slip Polycarbonate Desk Protector, 29 x 59 Inches, Rectangular, Clear (FPDE2949RA)","price":44.27,"thumbnail":"https://images-na.ssl-images-amazon.com/images/I/31mZ9QXiA2L._AC_US218_.jpg","description":null,"brand":"Floortex","detail_url":"https://www.amazon.com/dp/B005G2HY8I","query":"glass office desk ","query_group_id":0,"category":"Home & Kitchen"},{"adId":16,"campaignId":8115,"keyWords":["glass+office+desk+"],"relevanceScore":0.0,"pClick":0.0,"bidPrice":20.0,"rankScore":0.0,"qualityScore":0.0,"costPerClick":0.0,"position":0,"title":"Merax Computer Table with Glass Top and Metal Legs","price":112.16,"thumbnail":"https://images-na.ssl-images-amazon.com/images/I/51cL2kduOrL._AC_US218_.jpg","description":null,"brand":"Merax","detail_url":"https://www.amazon.com/dp/B01CG7SIZI","query":"glass office desk ","query_group_id":0,"category":"Home & Kitchen"},{"adId":16,"campaignId":8115,"keyWords":["glass+office+desk+"],"relevanceScore":0.0,"pClick":0.0,"bidPrice":20.0,"rankScore":0.0,"qualityScore":0.0,"costPerClick":0.0,"position":0,"title":"Calico Designs 50300 Jameson L-Shaped Computer Work Center with Clear Glass, Silver","price":104.27,"thumbnail":"https://images-na.ssl-images-amazon.com/images/I/41QHUTp5mzL._AC_US218_.jpg","description":null,"brand":"Calico Designs","detail_url":"https://www.amazon.com/dp/B003ZT884S","query":"glass office desk ","query_group_id":0,"category":"Home & Kitchen"},{"adId":16,"campaignId":8115,"keyWords":["glass+office+desk+"],"relevanceScore":0.0,"pClick":0.0,"bidPrice":20.0,"rankScore":0.0,"qualityScore":0.0,"costPerClick":0.0,"position":0,"title":"Biloba 4.8 Inch Puff Sand Timer/Hourglass 30 Minutes - Copper Color Sand - Inspired Glass/Home , Desk , Office Decor","price":9.99,"thumbnail":"https://images-na.ssl-images-amazon.com/images/I/31gi2rUKuNL._AC_US218_.jpg","description":null,"brand":"Biloba","detail_url":"https://www.amazon.com/dp/B01MDJYJ8U","query":"glass office desk ","query_group_id":0,"category":"Home & Kitchen"},{"adId":16,"campaignId":8115,"keyWords":["glass+office+desk+"],"relevanceScore":0.0,"pClick":0.0,"bidPrice":20.0,"rankScore":0.0,"qualityScore":0.0,"costPerClick":0.0,"position":0,"title":"Merax Glass Desk Top with Bookcase Home Workstation Office Metal Corner Desk Computer PC Glass Writing Table (Clear Glass)","price":59.9,"thumbnail":"https://images-na.ssl-images-amazon.com/images/I/51czS8pijsL._AC_US218_.jpg","description":null,"brand":"Merax","detail_url":"https://www.amazon.com/dp/B01LAV0PGQ","query":"glass office desk ","query_group_id":0,"category":"Home & Kitchen"},{"adId":16,"campaignId":8115,"keyWords":["glass+office+desk+"],"relevanceScore":0.0,"pClick":0.0,"bidPrice":20.0,"rankScore":0.0,"qualityScore":0.0,"costPerClick":0.0,"position":0,"title":"Acrylic Name Plate Office Desk Bar Custom Personalized Engraved","price":13.99,"thumbnail":"https://images-na.ssl-images-amazon.com/images/I/41GDExAZX7L._AC_US218_.jpg","description":null,"brand":"Caramel Sweet Life","detail_url":"https://www.amazon.com/dp/B01MZ6N62L","query":"glass office desk ","query_group_id":0,"category":"Home & Kitchen"},{"adId":16,"campaignId":8115,"keyWords":["glass+office+desk+"],"relevanceScore":0.0,"pClick":0.0,"bidPrice":20.0,"rankScore":0.0,"qualityScore":0.0,"costPerClick":0.0,"position":0,"title":"Studio Designs 50707 Calico Designs Colorado Desk, Black/Silver","price":68.27,"thumbnail":"https://images-na.ssl-images-amazon.com/images/I/31cl8INU2KL._AC_US218_.jpg","description":null,"brand":"Studio Designs","detail_url":"https://www.amazon.com/dp/B00X9Q0AZ2","query":"glass office desk ","query_group_id":0,"category":"Home & Kitchen"},{"adId":16,"campaignId":8115,"keyWords":["glass+office+desk+"],"relevanceScore":0.0,"pClick":0.0,"bidPrice":20.0,"rankScore":0.0,"qualityScore":0.0,"costPerClick":0.0,"position":0,"title":"Z-Line Claremont Desk","price":106.24,"thumbnail":"https://images-na.ssl-images-amazon.com/images/I/41vOQYtPKoL._AC_US218_.jpg","description":null,"brand":"Z-Line Designs","detail_url":"https://www.amazon.com/dp/B002FYGP5I","query":"glass office desk ","query_group_id":0,"category":"Home & Kitchen"},{"adId":16,"campaignId":8115,"keyWords":["glass+office+desk+"],"relevanceScore":0.0,"pClick":0.0,"bidPrice":20.0,"rankScore":0.0,"qualityScore":0.0,"costPerClick":0.0,"position":0,"title":"RTA Home and Office CT-009 Clear Glass and Aluminum Computer Desk","price":160.56,"thumbnail":"https://images-na.ssl-images-amazon.com/images/I/41HLzISDd4L._AC_US218_.jpg","description":null,"brand":"RTA Home and Office","detail_url":"https://www.amazon.com/dp/B004TN6LHU","query":"glass office desk ","query_group_id":0,"category":"Home & Kitchen"},{"adId":16,"campaignId":8115,"keyWords":["glass+office+desk+"],"relevanceScore":0.0,"pClick":0.0,"bidPrice":20.0,"rankScore":0.0,"qualityScore":0.0,"costPerClick":0.0,"position":0,"title":"WE Furniture 48\" Storage Computer Desk, Black","price":193.87,"thumbnail":"https://images-na.ssl-images-amazon.com/images/I/51trQyzXFML._AC_US218_.jpg","description":null,"brand":"WE Furniture","detail_url":"https://www.amazon.com/dp/B00FFU9O3O","query":"glass office desk ","query_group_id":0,"category":"Home & Kitchen"},{"adId":16,"campaignId":8115,"keyWords":["glass+office+desk+"],"relevanceScore":0.0,"pClick":0.0,"bidPrice":20.0,"rankScore":0.0,"qualityScore":0.0,"costPerClick":0.0,"position":0,"title":"Glass L-Shape Desk with Pull-Out Keyboard Tray","price":124.58,"thumbnail":"https://images-na.ssl-images-amazon.com/images/I/41cveyYwR0L._AC_US218_.jpg","description":null,"brand":"Flash Furniture","detail_url":"https://www.amazon.com/dp/B00BK31NMU","query":"glass office desk ","query_group_id":0,"category":"Home & Kitchen"},{"adId":16,"campaignId":8115,"keyWords":["glass+office+desk+"],"relevanceScore":0.0,"pClick":0.0,"bidPrice":20.0,"rankScore":0.0,"qualityScore":0.0,"costPerClick":0.0,"position":0,"title":"OGIMA Deluxe Tempered Glass Square Home Office Computer Desk-Black","price":0.0,"thumbnail":"https://images-na.ssl-images-amazon.com/images/I/51I8Jb+yecL._AC_US218_.jpg","description":null,"brand":"OGIMA","detail_url":"https://www.amazon.com/dp/B01ALHN990","query":"glass office desk ","query_group_id":0,"category":"Home & Kitchen"},{"adId":16,"campaignId":8115,"keyWords":["glass+office+desk+"],"relevanceScore":0.0,"pClick":0.0,"bidPrice":20.0,"rankScore":0.0,"qualityScore":0.0,"costPerClick":0.0,"position":0,"title":"Glass Desk with Black Pedestal Frame","price":94.99,"thumbnail":"https://images-na.ssl-images-amazon.com/images/I/41cSH1LWY5L._AC_US218_.jpg","description":null,"brand":"Flash Furniture","detail_url":"https://www.amazon.com/dp/B00VTQSP7E","query":"glass office desk ","query_group_id":0,"category":"Home & Kitchen"},{"adId":16,"campaignId":8115,"keyWords":["glass+office+desk+"],"relevanceScore":0.0,"pClick":0.0,"bidPrice":20.0,"rankScore":0.0,"qualityScore":0.0,"costPerClick":0.0,"position":0,"title":"Glass Computer Desk with Silver Frame","price":115.82,"thumbnail":"https://images-na.ssl-images-amazon.com/images/I/41YEPjtNwlL._AC_US218_.jpg","description":null,"brand":"Flash Furniture","detail_url":"https://www.amazon.com/dp/B00BK31LDQ","query":"glass office desk ","query_group_id":0,"category":"Home & Kitchen"},{"adId":16,"campaignId":8115,"keyWords":["glass+office+desk+"],"relevanceScore":0.0,"pClick":0.0,"bidPrice":20.0,"rankScore":0.0,"qualityScore":0.0,"costPerClick":0.0,"position":0,"title":"Small Standing Desk VARIDESK Laptop 30 Portable Stand Up Desk","price":175.0,"thumbnail":"https://images-na.ssl-images-amazon.com/images/I/416S7tf5W2L._AC_US218_.jpg","description":null,"brand":"VARIDESK","detail_url":"https://www.amazon.com/dp/B073BL7NH7","query":"glass office desk ","query_group_id":0,"category":"Home & Kitchen"},{"adId":16,"campaignId":8115,"keyWords":["glass+office+desk+"],"relevanceScore":0.0,"pClick":0.0,"bidPrice":20.0,"rankScore":0.0,"qualityScore":0.0,"costPerClick":0.0,"position":0,"title":"VARIDESK Pro Desk 48 Full Standing Desk (Butcher Block)","price":595.0,"thumbnail":"https://images-na.ssl-images-amazon.com/images/I/41HVsLiJoDL._AC_US218_.jpg","description":null,"brand":"VARIDESK","detail_url":"https://www.amazon.com/dp/B073T13D3H","query":"glass office desk ","query_group_id":0,"category":"Home & Kitchen"},{"adId":16,"campaignId":8115,"keyWords":["glass+office+desk+"],"relevanceScore":0.0,"pClick":0.0,"bidPrice":20.0,"rankScore":0.0,"qualityScore":0.0,"costPerClick":0.0,"position":0,"title":"VARIDESK Pro Desk 48 Full Standing Desk in Black","price":595.0,"thumbnail":"https://images-na.ssl-images-amazon.com/images/I/41ogYbUarML._AC_US218_.jpg","description":null,"brand":"VARIDESK","detail_url":"https://www.amazon.com/dp/B072Y6GXBB","query":"glass office desk ","query_group_id":0,"category":"Home & Kitchen"}]